macrostrat/database/__init__.py
macrostrat/database/mapper/__init__.py
macrostrat/database/mapper/base.py
macrostrat/database/mapper/cache.py
macrostrat/database/mapper/utils.py
macrostrat/database/postgresql.py
macrostrat/database/transfer/__init__.py
macrostrat/database/transfer/dump_database.py
macrostrat/database/transfer/move_tables.py
macrostrat/database/transfer/restore_database.py
macrostrat/database/transfer/stream_utils.py
macrostrat/database/transfer/utils.py
macrostrat/database/utils.py
macrostrat_database-3.5.4.dist-info/METADATA
macrostrat_database-3.5.4.dist-info/WHEEL
macrostrat_database-3.5.4.dist-info/RECORD
