Metadata-Version: 2.1
Name: macrostrat.database
Version: 3.5.4
Summary: A SQLAlchemy-based database toolkit.
Author: Daven Quinn
Author-email: dev@davenquinn.com
Requires-Python: >=3.10,<4.0
Classifier: Programming Language :: Python :: 3
Classifier: Programming Language :: Python :: 3.10
Classifier: Programming Language :: Python :: 3.11
Classifier: Programming Language :: Python :: 3.12
Requires-Dist: GeoAlchemy2 (>=0.15.2,<0.16.0)
Requires-Dist: SQLAlchemy (>=2.0.18,<3.0.0)
Requires-Dist: SQLAlchemy-Utils (>=0.41.1,<0.42.0)
Requires-Dist: aiofiles (>=23.2.1,<24.0.0)
Requires-Dist: click (>=8.1.3,<9.0.0)
Requires-Dist: macrostrat.utils (>=1.3.0,<2.0.0)
Requires-Dist: psycopg2-binary (>=2.9.6,<3.0.0)
Requires-Dist: rich (>=13.7.1,<14.0.0)
Requires-Dist: sqlparse (>=0.5.1,<0.6.0)
